{
  "assetsByChunkName": {
    "vendors~app-account~app-checkout~app-confirmation~app-order": "chunk.5f7944b50001669bdb89.js",
    "vendors~app-account~app-confirmation~app-order": "chunk.e8e917d001bf0a1d6a11.js",
    "vendors~app-account~app-checkout": "chunk.10fadb12989306775b0b.js",
    "admin": [
      "admin.fa1e21bf3ce7bb475fac.js",
      "admin.fa1e21bf3ce7bb475fac.js.map"
    ],
    "app-account": "chunk.e0f947788cfe55903ae3.js",
    "app-confirmation": "chunk.6d2d2f9279429b09c817.js",
    "app-order": "chunk.e2ff28b177d050245ae5.js",
    "checkout": [
      "checkout.4419c50fb8f1d7a1de90.js",
      "checkout.4419c50fb8f1d7a1de90.js.map"
    ],
    "storefront": [
      "storefront.d44f73e2a5704b6fb10f.css",
      "storefront.88059bc3148af752c1d6.js",
      "storefront.d44f73e2a5704b6fb10f.css.map",
      "storefront.88059bc3148af752c1d6.js.map"
    ],
    "vendors~app-cart": "chunk.0d7c528d5841a4aa5e22.js",
    "vendors~app-checkout": "chunk.68bf5f30842119dfa132.js"
  }
}